perceiver/__init__.py
perceiver/attention.py
perceiver/feedforward.py
perceiver/fourier_encode.py
perceiver/geglu.py
perceiver/perceiver.py
perceiver/prenorm.py
perceiver/version.py
perceiver-0.1.2.dist-info/LICENSE
perceiver-0.1.2.dist-info/METADATA
perceiver-0.1.2.dist-info/WHEEL
perceiver-0.1.2.dist-info/top_level.txt
perceiver-0.1.2.dist-info/RECORD
