Metadata-Version: 2.1
Name: perceiver
Version: 0.1.2
Summary: Implement of Perceiver, General Perception with Iterative Attention in TensorFlow
Home-page: https://github.com/Rishit-dagli/Perceiver
Author: Rishit Dagli
Author-email: rishit.dagli@gmail.com
License: UNKNOWN
Keywords: perceiver,artificial intelligence,deep learning,transformer,attention mechanism
Platform: UNKNOWN
Classifier: Development Status :: 4 - Beta
Classifier: Programming Language :: Python :: 3
Classifier: Programming Language :: Python :: 3 :: Only
Classifier: Programming Language :: Python :: 3.7
Classifier: Programming Language :: Python :: 3.8
Classifier: Programming Language :: Python :: 3.9
Classifier: License :: OSI Approved :: MIT License
Classifier: Intended Audience :: Developers
Classifier: Intended Audience :: Education
Classifier: Intended Audience :: Science/Research
Classifier: Topic :: Scientific/Engineering
Classifier: Topic :: Scientific/Engineering :: Artificial Intelligence
Classifier: Topic :: Software Development
Classifier: Topic :: Software Development :: Libraries
Classifier: Topic :: Software Development :: Libraries :: Python Modules
Classifier: Topic :: Scientific/Engineering :: Mathematics
Requires-Dist: tensorflow (~=2.4.0)
Requires-Dist: einops (>=0.3)
Provides-Extra: dev
Requires-Dist: check-manifest ; extra == 'dev'
Requires-Dist: twine ; extra == 'dev'
Requires-Dist: numpy ; extra == 'dev'
